clappform_ijsseldal/__init__.py
clappform_ijsseldal-0.0.4.dist-info/METADATA
clappform_ijsseldal-0.0.4.dist-info/WHEEL
clappform_ijsseldal-0.0.4.dist-info/top_level.txt
clappform_ijsseldal-0.0.4.dist-info/RECORD
