Metadata-Version: 2.1
Name: clappform-ijsseldal
Version: 0.0.4
Summary: Clappform Python API wrapper
Author-email: "Clappform B.V." <info@clappform.com>
Project-URL: Documentation, https://clappform.readthedocs.io
Project-URL: Source, https://github.com/ClappFormOrg/clappform-ijsseldal
Classifier: Development Status :: 1 - Planning
Classifier: License :: OSI Approved :: MIT License
Classifier: Programming Language :: Python :: 3
Classifier: Operating System :: OS Independent
Requires-Python: >=3.10
Requires-Dist: requests ==2.31.0
Requires-Dist: pandas ==1.5.2
